mupifAccel/__init__.py
mupifAccel/fastOctant.cpython-39-darwin.so
mupifAccel/include/eigen3/signature_of_eigen3_matrix_library
mupifAccel/include/eigen3/Eigen/Cholesky
mupifAccel/include/eigen3/Eigen/CholmodSupport
mupifAccel/include/eigen3/Eigen/Core
mupifAccel/include/eigen3/Eigen/Dense
mupifAccel/include/eigen3/Eigen/Eigen
mupifAccel/include/eigen3/Eigen/Eigenvalues
mupifAccel/include/eigen3/Eigen/Geometry
mupifAccel/include/eigen3/Eigen/Householder
mupifAccel/include/eigen3/Eigen/IterativeLinearSolvers
mupifAccel/include/eigen3/Eigen/Jacobi
mupifAccel/include/eigen3/Eigen/KLUSupport
mupifAccel/include/eigen3/Eigen/LU
mupifAccel/include/eigen3/Eigen/MetisSupport
mupifAccel/include/eigen3/Eigen/OrderingMethods
mupifAccel/include/eigen3/Eigen/PaStiXSupport
mupifAccel/include/eigen3/Eigen/PardisoSupport
mupifAccel/include/eigen3/Eigen/QR
mupifAccel/include/eigen3/Eigen/QtAlignedMalloc
mupifAccel/include/eigen3/Eigen/SPQRSupport
mupifAccel/include/eigen3/Eigen/SVD
mupifAccel/include/eigen3/Eigen/Sparse
mupifAccel/include/eigen3/Eigen/SparseCholesky
mupifAccel/include/eigen3/Eigen/SparseCore
mupifAccel/include/eigen3/Eigen/SparseLU
mupifAccel/include/eigen3/Eigen/SparseQR
mupifAccel/include/eigen3/Eigen/StdDeque
mupifAccel/include/eigen3/Eigen/StdList
mupifAccel/include/eigen3/Eigen/StdVector
mupifAccel/include/eigen3/Eigen/SuperLUSupport
mupifAccel/include/eigen3/Eigen/UmfPackSupport
mupifAccel/include/eigen3/Eigen/src/Cholesky/LDLT.h
mupifAccel/include/eigen3/Eigen/src/Cholesky/LLT.h
mupifAccel/include/eigen3/Eigen/src/Cholesky/LLT_LAPACKE.h
mupifAccel/include/eigen3/Eigen/src/CholmodSupport/CholmodSupport.h
mupifAccel/include/eigen3/Eigen/src/Core/ArithmeticSequence.h
mupifAccel/include/eigen3/Eigen/src/Core/Array.h
mupifAccel/include/eigen3/Eigen/src/Core/ArrayBase.h
mupifAccel/include/eigen3/Eigen/src/Core/ArrayWrapper.h
mupifAccel/include/eigen3/Eigen/src/Core/Assign.h
mupifAccel/include/eigen3/Eigen/src/Core/AssignEvaluator.h
mupif_accel-0.0.2.dist-info/LICENSE.txt
mupif_accel-0.0.2.dist-info/METADATA
mupif_accel-0.0.2.dist-info/WHEEL
mupif_accel-0.0.2.dist-info/top_level.txt
mupif_accel-0.0.2.dist-info/RECORD
